{
  "properties": {
    "name": { "type": "string", "maxLength": 200, "minLength": 1, "title": "Name" },
    "city": { "anyOf": [{ "type": "string" }, { "type": "null" }], "title": "City" },
    "state": {
      "anyOf": [{ "type": "string", "maxLength": 2 }, { "type": "null" }],
      "title": "State"
    },
    "country": { "type": "string", "maxLength": 100, "title": "Country", "default": "Brasil" },
    "latitude": { "anyOf": [{ "type": "number" }, { "type": "null" }], "title": "Latitude" },
    "longitude": { "anyOf": [{ "type": "number" }, { "type": "null" }], "title": "Longitude" },
    "id": { "type": "integer", "title": "Id" },
    "created_at": { "type": "string", "format": "date-time", "title": "Created At" },
    "updated_at": { "type": "string", "format": "date-time", "title": "Updated At" }
  },
  "type": "object",
  "required": ["name", "id", "created_at", "updated_at"],
  "title": "Regiao",
  "x-readme-ref-name": "Regiao"
}
